aioschluter/__init__.py
aioschluter/const.py
aioschluter/thermostat.py
aioschluter-0.1.9.dist-info/LICENSE
aioschluter-0.1.9.dist-info/METADATA
aioschluter-0.1.9.dist-info/WHEEL
aioschluter-0.1.9.dist-info/top_level.txt
aioschluter-0.1.9.dist-info/RECORD
