Metadata-Version: 2.1
Name: aioschluter
Version: 0.1.9
Summary: Async Python wrapper for the Schluter-DITRA-E-WIFI thermostats API.
Home-page: https://github.com/IngoS11/aioschluter
Author: Ingo Sauerzapf 
License: MIT License
Platform: UNKNOWN
Classifier: Development Status :: 3 - Alpha
Classifier: License :: OSI Approved :: MIT License
Classifier: Operating System :: OS Independent
Classifier: Programming Language :: Python
Classifier: Programming Language :: Python :: 3
Classifier: Programming Language :: Python :: 3.9
Classifier: Programming Language :: Python :: 3.10
Classifier: Programming Language :: Python :: 3 :: Only
Classifier: Typing :: Typed
Requires-Python: >=3.9
License-File: LICENSE
Requires-Dist: aiohttp (>=3.7.0)
